easychat/WXBizMsgCrypt3.py
easychat/__init__.py
easychat/easychat.py
easychat/ierror.py
easychat/wework.py
easychat-0.1.1.dist-info/LICENSE
easychat-0.1.1.dist-info/METADATA
easychat-0.1.1.dist-info/WHEEL
easychat-0.1.1.dist-info/top_level.txt
easychat-0.1.1.dist-info/RECORD
