Metadata-Version: 2.1
Name: easychat
Version: 0.1.1
Summary: A simple chatbot framework
Home-page: https://github.com/simpx/easychat
Author: simpx
Author-email: simpxx@gmail.com
License: MIT
Platform: UNKNOWN
Classifier: Development Status :: 3 - Alpha
Classifier: Intended Audience :: Developers
Classifier: License :: OSI Approved :: MIT License
Classifier: Programming Language :: Python :: 3
Classifier: Programming Language :: Python :: 3.7
Classifier: Programming Language :: Python :: 3.8
Classifier: Programming Language :: Python :: 3.9
License-File: LICENSE
Requires-Dist: Flask
Requires-Dist: PyYAML
Requires-Dist: pycryptodome
